simple_postgres_setup/__init__.py
simple_postgres_setup/changelog
simple_postgres_setup/code/__init__.py
simple_postgres_setup/code/core/__init__.py
simple_postgres_setup/code/core/create_database.py
simple_postgres_setup/code/core/create_extensions.py
simple_postgres_setup/code/core/create_local_folders_and_files.py
simple_postgres_setup/code/core/create_policies.py
simple_postgres_setup/code/core/create_schemas.py
simple_postgres_setup/code/core/create_users.py
simple_postgres_setup/code/core/prepare_subscription.py
simple_postgres_setup/code/core/read_configuration.py
simple_postgres_setup/code/core/rollback_and_cleanup_all.py
simple_postgres_setup/code/utils/__init__.py
simple_postgres_setup/code/utils/db_connect.py
simple_postgres_setup/code/utils/execute_statement.py
simple_postgres_setup/code/utils/random_password_generator.py
simple_postgres_setup/code/utils/write_to_log.py
simple_postgres_setup/code/utils/write_to_setup_statements.py
simple_postgres_setup/code/utils/write_to_undo_statements.py
simple_postgres_setup/main.py
simple_postgres_setup/templates/.env.example
simple_postgres_setup/templates/config.yml.example
simple_postgres_setup-0.2.1.dist-info/METADATA
simple_postgres_setup-0.2.1.dist-info/WHEEL
simple_postgres_setup-0.2.1.dist-info/licenses/LICENSE
simple_postgres_setup-0.2.1.dist-info/RECORD
