Metadata-Version: 2.4
Name: simple_postgres_setup
Version: 0.2.1
Summary: simple_postgres_setup is a python utility for deploying PostgreSQL databases from a yaml configuration file.
License: MIT
License-File: LICENSE
Author: Matthias Daues
Author-email: matthias.daues@datenschoenheit.de
Requires-Python: >=3.10
Classifier: License :: OSI Approved :: MIT License
Classifier: Programming Language :: Python :: 3
Classifier: Programming Language :: Python :: 3.10
Classifier: Programming Language :: Python :: 3.11
Classifier: Programming Language :: Python :: 3.12
Classifier: Programming Language :: Python :: 3.13
Classifier: Programming Language :: Python :: 3.14
Requires-Dist: aiosql (>=10.2)
Requires-Dist: psycopg2-binary (>=2.9.6)
Requires-Dist: pyyaml (>=6.0.1)
Requires-Dist: sqlalchemy (>=2.0.15,<3.0.0)
Requires-Dist: sqlalchemy-utils (==0.41.1)
